LICENSE
midnite/__init__.py
midnite/common.py
midnite/uncertainty/__init__.py
midnite/uncertainty/functional.py
midnite/uncertainty/modules.py
midnite/visualization/__init__.py
midnite/visualization/base/__init__.py
midnite/visualization/base/interface.py
midnite/visualization/base/methods/__init__.py
midnite/visualization/base/methods/backpropagation.py
midnite/visualization/base/methods/common.py
midnite/visualization/base/methods/gradam.py
midnite/visualization/base/methods/occlusion.py
midnite/visualization/base/methods/pixel_activation.py
midnite/visualization/base/splits.py
midnite/visualization/base/transforms.py
midnite/visualization/compound_methods.py
midnite-0.1.2.dist-info/LICENSE
midnite-0.1.2.dist-info/WHEEL
midnite-0.1.2.dist-info/METADATA
midnite-0.1.2.dist-info/RECORD
