Metadata-Version: 2.1
Name: midnite
Version: 0.1.2
Summary: This is a framework for visualization and uncertainty in CNNs.
Home-page: https://luminovo.gitlab.io/public/midnite
License: MIT
Keywords: torch,pytorch,uncertainty,classification,segmentation,visualization,GradCAM,occlusion,CNN
Author: luminovo.ai, Christina Aigner, Fabian Huch
Requires-Python: >=3.7,<4.0
Classifier: Intended Audience :: Developers
Classifier: Intended Audience :: Science/Research
Classifier: License :: OSI Approved :: MIT License
Classifier: Programming Language :: Python :: 3
Classifier: Programming Language :: Python :: 3.7
Classifier: Topic :: Scientific/Engineering :: Image Recognition
Classifier: Topic :: Scientific/Engineering :: Visualization
Requires-Dist: numpy (>=1.16,<2.0)
Requires-Dist: opencv-python (>=4.0,<5.0)
Requires-Dist: pillow (>=6.1,<7.0)
Requires-Dist: torch (==1.1)
Requires-Dist: tqdm (>=4.31,<5.0)
Project-URL: Repository, https://gitlab.com/luminovo/public/midnite
